bowler/LICENSE
bowler/README.md
bowler/__init__.py
bowler/__main__.py
bowler/helpers.py
bowler/imr.py
bowler/main.py
bowler/py.typed
bowler/query.py
bowler/tool.py
bowler/type_inference.py
bowler/types.py
waterloo/__about__.py
waterloo/__init__.py
waterloo/cli.py
waterloo/conf/__init__.py
waterloo/conf/types.py
waterloo/parsers/__init__.py
waterloo/parsers/napoleon.py
waterloo/parsers/python.py
waterloo/parsers/utils.py
waterloo/printer.py
waterloo/py.typed
waterloo/refactor/__init__.py
waterloo/refactor/annotations.py
waterloo/refactor/base.py
waterloo/refactor/exceptions.py
waterloo/refactor/reporter.py
waterloo/refactor/utils.py
waterloo/types.py
waterloo-0.7.10.dist-info/entry_points.txt
waterloo-0.7.10.dist-info/WHEEL
waterloo-0.7.10.dist-info/METADATA
waterloo-0.7.10.dist-info/RECORD
