Metadata-Version: 2.1
Name: waterloo
Version: 0.7.10
Summary: Tool to convert 'typed docstrings' (i.e. Sphinx 'Napoleon' format) to PEP-484 Py2 type comments.
Home-page: https://github.com/anentropic/python-waterloo
License: MIT
Author: Anentropic
Author-email: ego@anentropic.com
Requires-Python: >=3.7,<3.9
Classifier: License :: OSI Approved :: MIT License
Classifier: Programming Language :: Python :: 3
Classifier: Programming Language :: Python :: 3.7
Classifier: Programming Language :: Python :: 3.8
Requires-Dist: attrs (>=20.1.0,<21.0.0)
Requires-Dist: click (>=7.1.2,<8.0.0)
Requires-Dist: colorama (>=0.4.3,<0.5.0)
Requires-Dist: fissix (>=19.2b1,<20.0)
Requires-Dist: inject (>=4.3.1,<5.0.0)
Requires-Dist: megaparsy (>=0.1.4,<0.2.0)
Requires-Dist: moreorless (>=0.3.0,<0.4.0)
Requires-Dist: parso (>=0.7.0,<0.8.0)
Requires-Dist: prompt-toolkit (>=3.0.3,<4.0.0)
Requires-Dist: pydantic (>=1.6.1,<2.0.0)
Requires-Dist: regex (>=2020.2.20,<2021.0.0)
Requires-Dist: structlog (>=20.1.0,<21.0.0)
Requires-Dist: toml (>=0.10.0,<0.11.0)
Requires-Dist: typesystem (>=0.2.4,<0.3.0)
Requires-Dist: typing-extensions (>=3.7.4,<4.0.0)
